apsniper0673_grsheetmanager-0.1.4.dist-info/licenses/LICENSE
mygrsheetmanager/__init__.py
mygrsheetmanager/df_wish_list.py
mygrsheetmanager/gr_sheet_manager.py
mygrsheetmanager/gr_sheet_manager_client.py
mygrsheetmanager/gr_sheet_manager_server.py
mygrsheetmanager/single_trader_wish_list.py
apsniper0673_grsheetmanager-0.1.4.dist-info/METADATA
apsniper0673_grsheetmanager-0.1.4.dist-info/WHEEL
apsniper0673_grsheetmanager-0.1.4.dist-info/top_level.txt
apsniper0673_grsheetmanager-0.1.4.dist-info/RECORD
