Metadata-Version: 2.4
Name: apsniper0673_grsheetmanager
Version: 0.1.4
Summary: My grsheetmanager for APSniper0673
Author: apsniper0673
Requires-Python: >=3.8
License-File: LICENSE
Dynamic: license-file
